setup.py
flair/__init__.py
flair/data.py
flair/data_fetcher.py
flair/datasets.py
flair/embeddings.py
flair/file_utils.py
flair/nn.py
flair/training_utils.py
flair/embeddings/en/en.wiki.bpe.vs100000.model
flair/models/__init__.py
flair/models/sequence_tagger_model.py
flair_light.egg-info/PKG-INFO
flair_light.egg-info/SOURCES.txt
flair_light.egg-info/dependency_links.txt
flair_light.egg-info/requires.txt
flair_light.egg-info/top_level.txt