Metadata-Version: 1.2
Name: flair-light
Version: 0.4.2
Summary: A lightweight version of Flair for sequence tagging.
Home-page: UNKNOWN
Author: snapADDY GmbH
Author-email: info@snapaddy.com
License: UNKNOWN
Platform: UNKNOWN
Requires-Python: >=3.6,<4.0
